{
    "idSave": 466,
    "isFirstSession": false,
    "language": "ru",
    "promptDone": false,
    "SkipAd": true,
    "Money": 2196,
    "BestScore": 15,
    "OpenSkins": [
        true,
        false,
        false,
        false,
        false,
        false,
        false,
        false,
        false,
        false,
        false,
        false,
        false,
        false,
        false,
        false,
        false,
        false,
        false,
        false
    ],
    "IntOpenSkins": [
        1,
        1,
        0,
        0,
        0,
        0,
        1,
        0,
        1,
        1,
        1,
        1,
        0,
        0,
        0,
        1,
        0,
        0,
        1,
        0
    ],
    "PlayerSkinId": 6,
    "SoundValue": 0.1968422830104828,
    "MusicValue": 0.019999999552965165,
    "EffectsEnabled": true
}